eo4eu_comm_utils/__init__.py
eo4eu_comm_utils/comms/__init__.py
eo4eu_comm_utils/comms/dispatcher.py
eo4eu_comm_utils/comms/dummy.py
eo4eu_comm_utils/comms/interface.py
eo4eu_comm_utils/comms/log.py
eo4eu_comm_utils/comms/modify.py
eo4eu_comm_utils/comms/monitoring.py
eo4eu_comm_utils/comms/prometheus.py
eo4eu_comm_utils/comms/topic.py
eo4eu_comm_utils/format/__init__.py
eo4eu_comm_utils/format/default.py
eo4eu_comm_utils/format/interface.py
eo4eu_comm_utils/format/log.py
eo4eu_comm_utils/format/term.py
eo4eu_comm_utils/kafka/__init__.py
eo4eu_comm_utils/kafka/consumer.py
eo4eu_comm_utils/kafka/producer.py
eo4eu_comm_utils/settings/__init__.py
eo4eu_comm_utils-1.6.0.dist-info/METADATA
eo4eu_comm_utils-1.6.0.dist-info/WHEEL
eo4eu_comm_utils-1.6.0.dist-info/top_level.txt
eo4eu_comm_utils-1.6.0.dist-info/RECORD
