Metadata-Version: 2.4
Name: eo4eu_comm_utils
Version: 1.6.0
Summary: General messaging utilities for EO4EU
Author-email: Apollon Grigoras <apollon@uoa.gr>
Classifier: Programming Language :: Python :: 3
Classifier: Programming Language :: Python :: 3.10
Classifier: Programming Language :: Python :: 3.11
Classifier: Programming Language :: Python :: 3.12
Classifier: License :: OSI Approved :: MIT License
Classifier: Operating System :: OS Independent
Requires-Python: >=3.10
Requires-Dist: eo4eu_base_utils>=0.4.6
Provides-Extra: kafka
Requires-Dist: confluent-kafka>=2.1.1; python_version <= "3.11" and extra == "kafka"
Requires-Dist: confluent-kafka>=2.3.0; python_version == "3.12" and extra == "kafka"
Provides-Extra: prometheus
Requires-Dist: prometheus-client~=0.16.0; python_version <= "3.11" and extra == "prometheus"
Requires-Dist: prometheus-client>=0.16.0; python_version == "3.12" and extra == "prometheus"
Provides-Extra: full
Requires-Dist: eo4eu_comm_utils[kafka,prometheus]; extra == "full"
Provides-Extra: docs
Requires-Dist: eo4eu_comm_utils[full]; extra == "docs"
Requires-Dist: sphinx==8.2.3; extra == "docs"
Requires-Dist: sphinx-rtd-theme==3.0.2; extra == "docs"
